pywrappers/__init__.py
pywrappers/pymongo/CollectionWrapper.py
pywrappers/pymongo/DatabaseWrapper.py
pywrappers/pymongo/MongoClientWrapper.py
pywrappers/pymongo/__init__.py
pywrappers-1.0.5.dist-info/METADATA
pywrappers-1.0.5.dist-info/WHEEL
pywrappers-1.0.5.dist-info/top_level.txt
pywrappers-1.0.5.dist-info/RECORD
