Metadata-Version: 2.1
Name: pywrappers
Version: 1.0.5
Summary: A package that provides compatibility wrappers for different python libraries.
Author-email: Paulo Mol <paulo.junior@robbyson.com>
License: MIT
Project-URL: Homepage, https://gitlab.com/Robbyson/pywrappers
Project-URL: Bug Tracker, https://gitlab.com/Robbyson/pywrappers/issues
Requires-Python: >=3.7
Requires-Dist: pymongo[srv] >=4.5
Requires-Dist: typing-extensions >=4.0 ; python_version < "3.8"
Requires-Dist: importlib-metadata >=1.7.0 ; python_version < "3.8"
